sagapay/__init__.py
sagapay/client.py
sagapay/exceptions.py
sagapay/models.py
sagapay/webhook.py
sagapay-0.3.0.dist-info/METADATA
sagapay-0.3.0.dist-info/WHEEL
sagapay-0.3.0.dist-info/top_level.txt
sagapay-0.3.0.dist-info/RECORD
