Metadata-Version: 2.4
Name: sagapay
Version: 0.3.0
Summary: Python SDK for SagaPay - The world's first free, non-custodial blockchain payment gateway
Home-page: https://github.com/sagapay/sagapay-python
Author: SagaPay Team
Author-email: support@sagapay.net
Project-URL: Bug Tracker, https://github.com/sagapay/sagapay-python/issues
Project-URL: Documentation, https://sagapay.net/docs
Project-URL: Source Code, https://github.com/sagapay/sagapay-python
Keywords: blockchain,payment,cryptocurrency,api,gateway,sagapay
Classifier: Development Status :: 4 - Beta
Classifier: Intended Audience :: Developers
Classifier: License :: OSI Approved :: MIT License
Classifier: Programming Language :: Python :: 3
Classifier: Programming Language :: Python :: 3.7
Classifier: Programming Language :: Python :: 3.8
Classifier: Programming Language :: Python :: 3.9
Classifier: Programming Language :: Python :: 3.10
Classifier: Programming Language :: Python :: 3.11
Classifier: Programming Language :: Python :: 3.12
Classifier: Topic :: Software Development :: Libraries :: Python Modules
Classifier: Topic :: Office/Business :: Financial
Requires-Python: >=3.7
Requires-Dist: requests>=2.25.0
Requires-Dist: pydantic>=2.0.0
Dynamic: author
Dynamic: author-email
Dynamic: classifier
Dynamic: description
Dynamic: description-content-type
Dynamic: home-page
Dynamic: keywords
Dynamic: project-url
Dynamic: requires-dist
Dynamic: requires-python
Dynamic: summary
